{
    "gulp": {
        "javascript": [
            "JavaScript/*.js"
        ],
        "templates": [
            "Templates/*"
        ],
        "ssp-libraries": [
            "SuiteScript/*.js"
        ],
        "autogenerated-services": {
            "Address.Service.ss": "Address.ServiceController"
        },
        "sass": [
            "Sass/**/*.scss"
        ],
        "unit-test-files": [
            "Tests/*.js"
        ],
        "unit-test-entry-point": [
            "Tests/UnitTest.Address.js"
        ]
    }
    , "overrides": {
        "suitecommerce/Address@2.4.0/Templates/address_details.tpl" : "Templates/address_details.tpl"
        , "suitecommerce/Address@2.4.0/Templates/address_edit_fields.tpl" : "Templates/address_edit_fields.tpl"
    }
}